powerpetdoor/__init__.py
powerpetdoor/client.py
powerpetdoor/const.py
powerpetdoor/door.py
powerpetdoor/schedule.py
powerpetdoor/tz_utils.py
powerpetdoor/simulator/__init__.py
powerpetdoor/simulator/__main__.py
powerpetdoor/simulator/cli.py
powerpetdoor/simulator/protocol.py
powerpetdoor/simulator/scripting.py
powerpetdoor/simulator/server.py
powerpetdoor/simulator/state.py
powerpetdoor/simulator/scripts/basic_cycle.yaml
powerpetdoor/simulator/scripts/full_test_suite.yaml
powerpetdoor/simulator/scripts/obstruction_test.yaml
powerpetdoor/simulator/scripts/pet_presence_test.yaml
powerpetdoor/simulator/scripts/power_lockout_test.yaml
powerpetdoor/simulator/scripts/safety_lock_test.yaml
powerpetdoor/simulator/scripts/schedule_test.yaml
pypowerpetdoor-0.3.0.dist-info/licenses/LICENSE
pypowerpetdoor-0.3.0.dist-info/METADATA
pypowerpetdoor-0.3.0.dist-info/WHEEL
pypowerpetdoor-0.3.0.dist-info/top_level.txt
pypowerpetdoor-0.3.0.dist-info/RECORD
