Metadata-Version: 2.4
Name: pypowerpetdoor
Version: 0.3.0
Summary: Python library for communicating with Power Pet Door devices
Author-email: Preston Elder <prez@neuromancy.net>
License: MIT
Project-URL: Homepage, https://github.com/corporategoth/py-powerpetdoor
Project-URL: Repository, https://github.com/corporategoth/py-powerpetdoor
Project-URL: Issues, https://github.com/corporategoth/py-powerpetdoor/issues
Keywords: power pet door,pet door,home automation,iot
Classifier: Development Status :: 3 - Alpha
Classifier: Intended Audience :: Developers
Classifier: License :: OSI Approved :: MIT License
Classifier: Operating System :: OS Independent
Classifier: Programming Language :: Python :: 3
Classifier: Programming Language :: Python :: 3.11
Classifier: Programming Language :: Python :: 3.12
Classifier: Programming Language :: Python :: 3.13
Classifier: Programming Language :: Python :: 3.14
Classifier: Topic :: Home Automation
Requires-Python: >=3.11
License-File: LICENSE
Requires-Dist: async-timeout>=4.0.0
Requires-Dist: tzdata>=2024.1
Provides-Extra: dev
Requires-Dist: pytest>=7.0.0; extra == "dev"
Requires-Dist: pytest-asyncio>=0.21.0; extra == "dev"
Requires-Dist: pyyaml>=6.0; extra == "dev"
Dynamic: license-file
